can_logger/__init__.py
can_logger/__main__.py
can_logger/callbacks.py
can_logger/can_interface.py
can_logger/database.py
can_logger/database_tools/__init__.py
can_logger/database_tools/__main__.py
can_logger/database_tools/database_interface.py
can_logger/sniffer.py
cfdp_server/cfdp_reasemble.py
cfdp_server/cfdp_transfer.py
cfdp_server/checksum.py
can_logger-0.4.0.dist-info/METADATA
can_logger-0.4.0.dist-info/WHEEL
can_logger-0.4.0.dist-info/RECORD
