Metadata-Version: 2.3
Name: can-logger
Version: 0.4.0
Summary: 
License: MIT
Author: Adam Matusiak
Author-email: adammatusiak@icloude.com
Requires-Python: >=3.12,<4.0
Classifier: License :: OSI Approved :: MIT License
Classifier: Programming Language :: Python :: 3
Classifier: Programming Language :: Python :: 3.12
Classifier: Programming Language :: Python :: 3.13
Requires-Dist: aiosqlite (>=0.21.0,<0.22.0)
Requires-Dist: black (>=25.1.0,<26.0.0)
Requires-Dist: cantools (>=40.2.1,<41.0.0)
Requires-Dist: click (>=8.1.8,<9.0.0)
Requires-Dist: poethepoet (>=0.34.0,<0.35.0)
Requires-Dist: pytest (>=8.3.5,<9.0.0)
Requires-Dist: pytest-asyncio (>=0.23.6,<0.24.0)
Requires-Dist: pytest-mock (>=3.14.0,<4.0.0)
